nlptools/__init__.py
nlptools/cli.py
nlptools/nlptools.py
nlptools/DataDownload/__init__.py
nlptools/DataDownload/downloader.py
nlptools/arabiner/__init__.py
nlptools/arabiner/bin/__init__.py
nlptools/arabiner/bin/eval.py
nlptools/arabiner/bin/infer.py
nlptools/arabiner/bin/process.py
nlptools/arabiner/bin/train.py
nlptools/arabiner/data/__init__.py
nlptools/arabiner/data/datasets.py
nlptools/arabiner/data/transforms.py
nlptools/arabiner/nn/BaseModel.py
nlptools/arabiner/nn/BertNestedTagger.py
nlptools/arabiner/nn/BertSeqTagger.py
nlptools/arabiner/nn/__init__.py
nlptools/arabiner/utils/__init__.py
nlptools/arabiner/utils/data.py
nlptools/arabiner/utils/helpers.py
nlptools/arabiner/utils/metrics.py
nlptools/data/my_data.pickle
nlptools/morphology/ALMA_muli_word.py
nlptools/morphology/__init__.py
nlptools/morphology/alma_multi_word.py
nlptools/morphology/charsets.py
nlptools/morphology/morph_analyzer.py
nlptools/morphology/settings.py
nlptools/morphology/tokenizers_words.py
nlptools/salma/__init__.py
nlptools/salma/settings.py
nlptools/salma/views.py
nlptools/salma/wsd.py
nlptools/utils/__init__.py
nlptools/utils/corpus.py
nlptools/utils/implication.py
nlptools/utils/jaccard.py
nlptools/utils/parser.py
nlptools/utils/text_transliteration.py
nlptools/utils/tokenizer.py
nlptools/utils/utils.py
nlptoolssna-0.9.9.dist-info/AUTHORS.rst
nlptoolssna-0.9.9.dist-info/LICENSE
nlptoolssna-0.9.9.dist-info/METADATA
nlptoolssna-0.9.9.dist-info/WHEEL
nlptoolssna-0.9.9.dist-info/entry_points.txt
nlptoolssna-0.9.9.dist-info/top_level.txt
nlptoolssna-0.9.9.dist-info/RECORD
