Metadata-Version: 2.1
Name: nlptoolssna
Version: 0.9.9
Summary: Python Boilerplate contains all the boilerplate you need to create a Python package.
Home-page: https://github.com/eng-aomar/nlptools
Author: Alaa' Omar
Author-email: alaa.omer2009@gmail.com
License: MIT license
Keywords: nlptools
Classifier: Development Status :: 2 - Pre-Alpha
Classifier: Intended Audience :: Developers
Classifier: License :: OSI Approved :: MIT License
Classifier: Natural Language :: English
Classifier: Programming Language :: Python :: 3
Classifier: Programming Language :: Python :: 3.6
Classifier: Programming Language :: Python :: 3.7
Classifier: Programming Language :: Python :: 3.8
Classifier: Programming Language :: Python :: 3.9
Classifier: Programming Language :: Python :: 3.10
Requires-Python: >=3.6
License-File: LICENSE
License-File: AUTHORS.rst
Requires-Dist: six
Requires-Dist: farasapy
Requires-Dist: tqdm
Requires-Dist: requests
Requires-Dist: regex
Requires-Dist: pathlib
Requires-Dist: torch (==1.13.0)
Requires-Dist: transformers (==4.24.0)
Requires-Dist: torchtext (==0.14.0)
Requires-Dist: torchvision (==0.14.0)
Requires-Dist: seqeval (==1.2.2)
Requires-Dist: natsort (==7.1.1)
